{
  "networks": {
    "mainnet": {
      "chainId": 1,
      "name": "Ethereum Mainnet",
      "dexRouters": {
        "UNISWAP_V2": {
          "address": "0x7a250d5630B4cF539739dF2C5dAcb4c659F2488D",
          "type": "UniswapV2",
          "name": "Uniswap V2",
          "fee": 0.003,
          "active": true
        },
        "UNISWAP_V3": {
          "address": "0xE592427A0AEce92De3Edee1F18E0157C05861564",
          "type": "UniswapV3",
          "name": "Uniswap V3",
          "fee": 0.003,
          "active": true
        },
        "SUSHISWAP": {
          "address": "0xd9e1cE17f2641f24aE83637ab66a2cca9C378B9F",
          "type": "UniswapV2",
          "name": "SushiSwap",
          "fee": 0.003,
          "active": true
        },
        "BALANCER": {
          "address": "0xBA12222222228d8Ba445958a75a0704d566BF2C8",
          "type": "Balancer",
          "name": "Balancer V2",
          "fee": 0.001,
          "active": true
        },
        "CURVE": {
          "address": "0x99a58482BD75cbab83b27EC03CA68fF489b5788f",
          "type": "Curve",
          "name": "Curve Finance",
          "fee": 0.0004,
          "active": true
        },
        "ONEINCH": {
          "address": "0x1111111254EEB25477B68fb85Ed929f73A960582",
          "type": "1inch",
          "name": "1inch V5",
          "fee": 0.001,
          "active": true
        }
      },
      "tokens": {
        "WETH": {
          "address": "0xC02aaA39b223FE8D0A0e5C4F27eAD9083C756Cc2",
          "symbol": "WETH",
          "name": "Wrapped Ether",
          "decimals": 18,
          "active": true,
          "flashloanAmount": "10000000000000000000"
        },
        "USDC": {
          "address": "0xA0b86a33E6417c4c4c4c4c4c4c4c4c4c4c4c4c4c",
          "symbol": "USDC",
          "name": "USD Coin",
          "decimals": 6,
          "active": true,
          "flashloanAmount": "50000000000"
        },
        "USDT": {
          "address": "0xdAC17F958D2ee523a2206206994597C13D831ec7",
          "symbol": "USDT",
          "name": "Tether USD",
          "decimals": 6,
          "active": true,
          "flashloanAmount": "50000000000"
        },
        "DAI": {
          "address": "0x6B175474E89094C44Da98b954EedeAC495271d0F",
          "symbol": "DAI",
          "name": "Dai Stablecoin",
          "decimals": 18,
          "active": true,
          "flashloanAmount": "50000000000000000000000"
        },
        "WBTC": {
          "address": "0x2260FAC5E5542a773Aa44fBCfeDf7C193bc2C599",
          "symbol": "WBTC",
          "name": "Wrapped BTC",
          "decimals": 8,
          "active": true,
          "flashloanAmount": "100000000"
        }
      },
      "aave": {
        "addressProvider": "0x2f39d218133AFaB8F2B819B1066c7E434Ad94E9e",
        "pool": "0x87870Bace7f90c5c9b8102DE4e2E9c5984C8E1C8"
      }
    },
    "goerli": {
      "chainId": 5,
      "name": "Goerli Testnet",
      "dexRouters": {
        "UNISWAP_V2": {
          "address": "0x7a250d5630B4cF539739dF2C5dAcb4c659F2488D",
          "type": "UniswapV2",
          "name": "Uniswap V2",
          "fee": 0.003,
          "active": true
        },
        "UNISWAP_V3": {
          "address": "0xE592427A0AEce92De3Edee1F18E0157C05861564",
          "type": "UniswapV3",
          "name": "Uniswap V3",
          "fee": 0.003,
          "active": true
        }
      },
      "tokens": {
        "WETH": {
          "address": "0xB4FBF271143F4FBf7B91A5ded31805e42b2208d6",
          "symbol": "WETH",
          "name": "Wrapped Ether",
          "decimals": 18,
          "active": true,
          "flashloanAmount": "1000000000000000000"
        },
        "USDC": {
          "address": "0x07865c6E87B9F70255377e024ace6630C1Eaa37F",
          "symbol": "USDC",
          "name": "USD Coin",
          "decimals": 6,
          "active": true,
          "flashloanAmount": "1000000000"
        }
      },
      "aave": {
        "addressProvider": "0x5E52dEc931FFb32f609681B8438A51c675cc232d",
        "pool": "0x368EedF3f56ad10b9bC57eed4Dac65B26Bb667f6"
      }
    }
  },
  "gasSettings": {
    "mainnet": {
      "maxGasPrice": 100,
      "gasLimit": 800000,
      "priorityFee": 2
    },
    "goerli": {
      "maxGasPrice": 50,
      "gasLimit": 800000,
      "priorityFee": 1
    }
  },
  "profitSettings": {
    "minProfitUSD": 50,
    "slippageTolerance": 0.5,
    "maxSlippage": 3.0,
    "executionCooldown": 30000
  }
}
